ouseful_fsa_datasupply/__init__.py
ouseful_fsa_datasupply/cli.py
ouseful_fsa_datasupply/fsa.py
ouseful_fsa_datasupply/fsa_api.py
ouseful_fsa_datasupply-0.2.0.dist-info/LICENSE
ouseful_fsa_datasupply-0.2.0.dist-info/METADATA
ouseful_fsa_datasupply-0.2.0.dist-info/WHEEL
ouseful_fsa_datasupply-0.2.0.dist-info/entry_points.txt
ouseful_fsa_datasupply-0.2.0.dist-info/top_level.txt
ouseful_fsa_datasupply-0.2.0.dist-info/RECORD
