Metadata-Version: 2.2
Name: ouseful_fsa_datasupply
Version: 0.2.0
Summary: A simple tool for bulk downloading of etsablishment details and ratings data from food.gov.uk
Home-page: https://github.com/ouseful-datasupply/food_gov_uk
Author: Tony Hirst
Classifier: Programming Language :: Python :: 3.8
Classifier: Programming Language :: Python :: 3.7
Classifier: Programming Language :: Python :: 3.6
License-File: LICENSE
Requires-Dist: Click
Requires-Dist: requests
Requires-Dist: beautifulsoup4
Requires-Dist: pandas
Requires-Dist: xmltodict
Requires-Dist: tqdm
Requires-Dist: lxml
Requires-Dist: html5lib
Dynamic: author
Dynamic: classifier
Dynamic: description
Dynamic: description-content-type
Dynamic: home-page
Dynamic: requires-dist
Dynamic: summary
